sembump/__init__.py
sembump/bumper/__init__.py
sembump/bumper/exceptions.py
sembump/bumper/resolver.py
sembump/bumper/updater.py
sembump/bumper/walker.py
sembump/commands.py
sembump/plugins.py
poetry_plugin_sembump-1.0.1.dist-info/METADATA
poetry_plugin_sembump-1.0.1.dist-info/WHEEL
poetry_plugin_sembump-1.0.1.dist-info/entry_points.txt
poetry_plugin_sembump-1.0.1.dist-info/RECORD
