Metadata-Version: 2.1
Name: poetry-plugin-sembump
Version: 1.0.1
Summary: Bump the version of a poetry project dependencies.
Home-page: https://github.com/nullswan/poetry-plugin-sembump
License: MIT
Author: nullswan
Author-email: dev@nullswan.io
Requires-Python: >=3.8,<4.0
Classifier: License :: OSI Approved :: MIT License
Classifier: Programming Language :: Python :: 3
Classifier: Programming Language :: Python :: 3.8
Classifier: Programming Language :: Python :: 3.9
Classifier: Programming Language :: Python :: 3.10
Classifier: Programming Language :: Python :: 3.11
Classifier: Programming Language :: Python :: 3.12
Requires-Dist: poetry (>=1.5.0,<2.0.0)
Project-URL: Repository, https://github.com/nullswan/poetry-plugin-sembump
